{
  "parent": "minecraft:recipes/root",
  "rewards": {
    "recipes": [
      "tretackshop:7_fuchsia/english_saddle_7_from_saddle"
    ]
  },
  "criteria": {
    "has_english_saddle": {
      "trigger": "minecraft:inventory_changed",
      "conditions": {
        "items": [
          {
            "tag": "tretackshop:craft/english_saddles"
          }
        ]
      }
    },
    "has_the_recipe": {
      "trigger": "minecraft:recipe_unlocked",
      "conditions": {
        "recipe": "tretackshop:7_fuchsia/english_saddle_7_from_saddle"
      }
    }
  },
  "requirements": [
    [
      "has_english_saddle",
      "has_the_recipe"
    ]
  ]
}